{"fundId":"fh-allround","reportType":"monthly_top10","period":"2026-02","source":"joy88-seed","fetchedAt":"2026-05-27T15:32:22.533Z","holdings":[{"code":"2383","name":"台光電","weightPct":9.74,"rank":1,"amount":732000000,"market":"國內上市"},{"code":"8299","name":"群聯","weightPct":9.31,"rank":2,"amount":699300000,"market":"國內上櫃"},{"code":"2330","name":"台積電","weightPct":8.9,"rank":3,"amount":668325000,"market":"國內上市"},{"code":"2408","name":"南亞科","weightPct":8.55,"rank":4,"amount":642375000,"market":"國內上市"},{"code":"2308","name":"台達電","weightPct":8.38,"rank":5,"amount":629200000,"market":"國內上市"},{"code":"7769","name":"鴻勁","weightPct":7.76,"rank":6,"amount":583200000,"market":"國內上市"},{"code":"3037","name":"欣興","weightPct":7.31,"rank":7,"amount":548910000,"market":"國內上市"},{"code":"6223","name":"旺矽","weightPct":4.31,"rank":8,"amount":323950000,"market":"國內上櫃"},{"code":"3017","name":"奇鋐","weightPct":4.23,"rank":9,"amount":317700000,"market":"國內上市"},{"code":"6274","name":"台燿","weightPct":3.99,"rank":10,"amount":299750000,"market":"國內上櫃"}],"meta":{"manager":"呂宏宇","aum":75.1}}