{"fundId":"fh-allround","reportType":"quarterly_full","period":"2023-Q2","source":"joy88-seed","fetchedAt":"2026-05-27T15:32:22.533Z","holdings":[{"code":"3443","name":"創意","weightPct":6.27,"rank":1,"amount":208650000,"market":"國內上市"},{"code":"3661","name":"世芯-KY","weightPct":5.94,"rank":2,"amount":197450000,"market":"國內上市"},{"code":"3653","name":"健策","weightPct":5.24,"rank":3,"amount":174150000,"market":"國內上市"},{"code":"2330","name":"台積電","weightPct":5.2,"rank":4,"amount":172800000,"market":"國內上市"},{"code":"2382","name":"廣達","weightPct":4.3,"rank":5,"amount":142880000,"market":"國內上市"},{"code":"1513","name":"中興電","weightPct":4.12,"rank":6,"amount":137000000,"market":"國內上市"},{"code":"2308","name":"台達電","weightPct":4.01,"rank":7,"amount":133321500,"market":"國內上市"},{"code":"3017","name":"奇鋐","weightPct":3.75,"rank":8,"amount":124660000,"market":"國內上市"},{"code":"2376","name":"技嘉","weightPct":3.66,"rank":9,"amount":121750000,"market":"國內上市"},{"code":"2301","name":"光寶科","weightPct":3.42,"rank":10,"amount":113850000,"market":"國內上市"},{"code":"8996","name":"高力","weightPct":3.36,"rank":11,"amount":111705000,"market":"國內上市"},{"code":"6669","name":"緯穎","weightPct":3.33,"rank":12,"amount":110760000,"market":"國內上市"},{"code":"2368","name":"金像電","weightPct":3.07,"rank":13,"amount":102200000,"market":"國內上市"},{"code":"1795","name":"美時","weightPct":2.94,"rank":14,"amount":97650000,"market":"國內上市"},{"code":"2383","name":"台光電","weightPct":2.89,"rank":15,"amount":96182500,"market":"國內上市"},{"code":"3515","name":"華擎","weightPct":2.81,"rank":16,"amount":93450000,"market":"國內上市"},{"code":"2345","name":"智邦","weightPct":2.73,"rank":17,"amount":90740000,"market":"國內上市"},{"code":"2731","name":"雄獅","weightPct":2.6,"rank":18,"amount":86377500,"market":"國內上市"},{"code":"2727","name":"王品","weightPct":2.54,"rank":19,"amount":84402500,"market":"國內上市"},{"code":"2707","name":"晶華","weightPct":2.5,"rank":20,"amount":83040000,"market":"國內上市"},{"code":"3533","name":"嘉澤","weightPct":2.46,"rank":21,"amount":81910700,"market":"國內上市"},{"code":"3529","name":"力旺","weightPct":4.32,"rank":22,"amount":143650000,"market":"國內上櫃"},{"code":"8069","name":"元太","weightPct":3.25,"rank":23,"amount":108000000,"market":"國內上櫃"},{"code":"8299","name":"群聯","weightPct":2.97,"rank":24,"amount":98760000,"market":"國內上櫃"},{"code":"5274","name":"信驊","weightPct":2.83,"rank":25,"amount":94050000,"market":"國內上櫃"},{"code":"3587","name":"閎康","weightPct":2.58,"rank":26,"amount":85840000,"market":"國內上櫃"},{"code":"3260","name":"威剛","weightPct":2.54,"rank":27,"amount":84550000,"market":"國內上櫃"}],"meta":{"manager":"呂宏宇","aum":75.1}}