{"fundId":"taishin-mainstream","reportType":"monthly_top10","period":"2025-06","source":"joy88-seed","fetchedAt":"2026-05-27T15:32:22.533Z","holdings":[{"code":"3363","name":"上詮","weightPct":5.81,"rank":1,"amount":47862500,"market":"國內上櫃"},{"code":"3661","name":"世芯-KY","weightPct":4.88,"rank":2,"amount":40235000,"market":"國內上市"},{"code":"2330","name":"台積電","weightPct":4.76,"rank":3,"amount":39220000,"market":"國內上市"},{"code":"3665","name":"貿聯-KY","weightPct":4.53,"rank":4,"amount":37312000,"market":"國內上市"},{"code":"2383","name":"台光電","weightPct":4.28,"rank":5,"amount":35280000,"market":"國內上市"},{"code":"2454","name":"聯發科","weightPct":4.25,"rank":6,"amount":35000000,"market":"國內上市"},{"code":"3019","name":"亞光","weightPct":4.24,"rank":7,"amount":34935000,"market":"國內上市"},{"code":"2368","name":"金像電","weightPct":4.12,"rank":8,"amount":33925000,"market":"國內上市"},{"code":"5234","name":"達興材料","weightPct":4.07,"rank":9,"amount":33500000,"market":"國內上市"},{"code":"6669","name":"緯穎","weightPct":3.68,"rank":10,"amount":30360000,"market":"國內上市"}],"meta":{"manager":"黃千雲","aum":16.8}}