{"fundId":"allianz-dabar","reportType":"monthly_top10","period":"2025-03","source":"joy88-seed","fetchedAt":"2026-05-27T15:32:22.533Z","holdings":[{"code":"2330","name":"台積電","weightPct":10.16,"rank":1,"amount":2439710000,"market":"國內上市"},{"code":"2454","name":"聯發科","weightPct":6.75,"rank":2,"amount":1620740000,"market":"國內上市"},{"code":"5269","name":"祥碩","weightPct":5.69,"rank":3,"amount":1365000000,"market":"國內上市"},{"code":"2345","name":"智邦","weightPct":5.03,"rank":4,"amount":1207872000,"market":"國內上市"},{"code":"3529","name":"力旺","weightPct":3.79,"rank":5,"amount":910000000,"market":"國內上櫃"},{"code":"3653","name":"健策","weightPct":3.62,"rank":6,"amount":868640000,"market":"國內上市"},{"code":"2357","name":"華碩","weightPct":3.57,"rank":7,"amount":858081000,"market":"國內上市"},{"code":"3017","name":"奇鋐","weightPct":3.19,"rank":8,"amount":766352000,"market":"國內上市"},{"code":"2383","name":"台光電","weightPct":2.73,"rank":9,"amount":655090000,"market":"國內上市"},{"code":"3665","name":"貿聯-KY","weightPct":2.66,"rank":10,"amount":639576000,"market":"國內上市"}],"meta":{"manager":"蕭惠中","aum":521.18}}