{"fundId":"allianz-dabar","reportType":"quarterly_full","period":"2023-Q4","source":"joy88-seed","fetchedAt":"2026-05-27T15:32:22.533Z","holdings":[{"code":"2330","name":"台積電","weightPct":9.28,"rank":1,"amount":2018572000,"market":"國內上市"},{"code":"3661","name":"世芯-KY","weightPct":8.4,"rank":2,"amount":1827450000,"market":"國內上市"},{"code":"3653","name":"健策","weightPct":5.7,"rank":3,"amount":1239628000,"market":"國內上市"},{"code":"2345","name":"智邦","weightPct":5.64,"rank":4,"amount":1227481000,"market":"國內上市"},{"code":"6515","name":"穎崴","weightPct":4.98,"rank":5,"amount":1083988000,"market":"國內上市"},{"code":"6669","name":"緯穎","weightPct":4.87,"rank":6,"amount":1058500000,"market":"國內上市"},{"code":"2455","name":"全新","weightPct":4.09,"rank":7,"amount":889972500,"market":"國內上市"},{"code":"1477","name":"聚陽","weightPct":3.66,"rank":8,"amount":795498000,"market":"國內上市"},{"code":"3017","name":"奇鋐","weightPct":2.94,"rank":9,"amount":640329215,"market":"國內上市"},{"code":"3533","name":"嘉澤","weightPct":2.8,"rank":10,"amount":609350020,"market":"國內上市"},{"code":"2382","name":"廣達","weightPct":2.7,"rank":11,"amount":586394000,"market":"國內上市"},{"code":"6415","name":"矽力*-KY","weightPct":2.33,"rank":12,"amount":507000000,"market":"國內上市"},{"code":"3443","name":"創意","weightPct":2.33,"rank":13,"amount":506340000,"market":"國內上市"},{"code":"2368","name":"金像電","weightPct":1.91,"rank":14,"amount":415159200,"market":"國內上市"},{"code":"1519","name":"華城","weightPct":1.69,"rank":15,"amount":367875000,"market":"國內上市"},{"code":"2383","name":"台光電","weightPct":1.61,"rank":16,"amount":351058000,"market":"國內上市"},{"code":"3037","name":"欣興","weightPct":1.54,"rank":17,"amount":333872000,"market":"國內上市"},{"code":"2408","name":"南亞科","weightPct":1.51,"rank":18,"amount":327678000,"market":"國內上市"},{"code":"9802","name":"鈺齊-KY","weightPct":1.41,"rank":19,"amount":307450500,"market":"國內上市"},{"code":"3529","name":"力旺","weightPct":8.01,"rank":20,"amount":1741950000,"market":"國內上櫃"},{"code":"5274","name":"信驊","weightPct":3.33,"rank":21,"amount":723840000,"market":"國內上櫃"},{"code":"3675","name":"德微","weightPct":2.48,"rank":22,"amount":540428745,"market":"國內上櫃"},{"code":"6683","name":"雍智科技","weightPct":1.26,"rank":23,"amount":274248000,"market":"國內上櫃"},{"code":"4979","name":"華星光","weightPct":1.06,"rank":24,"amount":230256000,"market":"國內上櫃"},{"code":"3362","name":"先進光","weightPct":1.06,"rank":25,"amount":230090000,"market":"國內上櫃"},{"code":"3587","name":"閎康","weightPct":1.05,"rank":26,"amount":228630968,"market":"國內上櫃"}],"meta":{"manager":"蕭惠中","aum":521.18}}