{"fundId":"uni-sme","reportType":"monthly_top10","period":"2025-11","source":"joy88-seed","fetchedAt":"2026-05-27T15:32:22.533Z","holdings":[{"code":"2368","name":"金像電","weightPct":7.52,"rank":1,"amount":196230000,"market":"國內上市"},{"code":"2383","name":"台光電","weightPct":7.07,"rank":2,"amount":184525000,"market":"國內上市"},{"code":"6274","name":"台燿","weightPct":7,"rank":3,"amount":182600000,"market":"國內上櫃"},{"code":"3665","name":"貿聯-KY","weightPct":6.47,"rank":4,"amount":168871290,"market":"國內上市"},{"code":"3017","name":"奇鋐","weightPct":6.17,"rank":5,"amount":160875000,"market":"國內上市"},{"code":"6223","name":"旺矽","weightPct":6,"rank":6,"amount":156630000,"market":"國內上櫃"},{"code":"6515","name":"穎崴","weightPct":5.75,"rank":7,"amount":149990000,"market":"國內上市"},{"code":"3443","name":"創意","weightPct":5.63,"rank":8,"amount":146900000,"market":"國內上市"},{"code":"2308","name":"台達電","weightPct":5.39,"rank":9,"amount":140732000,"market":"國內上市"},{"code":"2360","name":"致茂","weightPct":5.15,"rank":10,"amount":134316000,"market":"國內上市"}],"meta":{"manager":"莊承憲","aum":29.14}}